{
  "id": "1cad91e1-1427-402a-832b-e68d1e69d3a9",
  "prevId": "00000000-0000-0000-0000-000000000000",
  "version": "7",
  "dialect": "postgresql",
  "tables": {
    "public.friendships": {
      "name": "friendships",
      "schema": "",
      "columns": {
        "id": {
          "name": "id",
          "type": "uuid",
          "primaryKey": true,
          "notNull": true,
          "default": "gen_random_uuid()"
        },
        "requester_id": {
          "name": "requester_id",
          "type": "uuid",
          "primaryKey": false,
          "notNull": true
        },
        "addressee_id": {
          "name": "addressee_id",
          "type": "uuid",
          "primaryKey": false,
          "notNull": true
        },
        "status": {
          "name": "status",
          "type": "friendship_status",
          "typeSchema": "public",
          "primaryKey": false,
          "notNull": true,
          "default": "'pending'"
        },
        "created_at": {
          "name": "created_at",
          "type": "timestamp",
          "primaryKey": false,
          "notNull": true,
          "default": "now()"
        },
        "updated_at": {
          "name": "updated_at",
          "type": "timestamp",
          "primaryKey": false,
          "notNull": true,
          "default": "now()"
        }
      },
      "indexes": {
        "friendships_requester_addressee_uniq": {
          "name": "friendships_requester_addressee_uniq",
          "columns": [
            {
              "expression": "requester_id",
              "isExpression": false,
              "asc": true,
              "nulls": "last"
            },
            {
              "expression": "addressee_id",
              "isExpression": false,
              "asc": true,
              "nulls": "last"
            }
          ],
          "isUnique": true,
          "concurrently": false,
          "method": "btree",
          "with": {}
        },
        "friendships_requester_idx": {
          "name": "friendships_requester_idx",
          "columns": [
            {
              "expression": "requester_id",
              "isExpression": false,
              "asc": true,
              "nulls": "last"
            }
          ],
          "isUnique": false,
          "concurrently": false,
          "method": "btree",
          "with": {}
        },
        "friendships_addressee_idx": {
          "name": "friendships_addressee_idx",
          "columns": [
            {
              "expression": "addressee_id",
              "isExpression": false,
              "asc": true,
              "nulls": "last"
            }
          ],
          "isUnique": false,
          "concurrently": false,
          "method": "btree",
          "with": {}
        },
        "friendships_status_idx": {
          "name": "friendships_status_idx",
          "columns": [
            {
              "expression": "status",
              "isExpression": false,
              "asc": true,
              "nulls": "last"
            }
          ],
          "isUnique": false,
          "concurrently": false,
          "method": "btree",
          "with": {}
        }
      },
      "foreignKeys": {
        "friendships_requester_id_users_id_fk": {
          "name": "friendships_requester_id_users_id_fk",
          "tableFrom": "friendships",
          "tableTo": "users",
          "columnsFrom": [
            "requester_id"
          ],
          "columnsTo": [
            "id"
          ],
          "onDelete": "cascade",
          "onUpdate": "no action"
        },
        "friendships_addressee_id_users_id_fk": {
          "name": "friendships_addressee_id_users_id_fk",
          "tableFrom": "friendships",
          "tableTo": "users",
          "columnsFrom": [
            "addressee_id"
          ],
          "columnsTo": [
            "id"
          ],
          "onDelete": "cascade",
          "onUpdate": "no action"
        }
      },
      "compositePrimaryKeys": {},
      "uniqueConstraints": {},
      "policies": {},
      "checkConstraints": {},
      "isRLSEnabled": false
    },
    "public.users": {
      "name": "users",
      "schema": "",
      "columns": {
        "id": {
          "name": "id",
          "type": "uuid",
          "primaryKey": true,
          "notNull": true,
          "default": "gen_random_uuid()"
        },
        "email": {
          "name": "email",
          "type": "varchar(255)",
          "primaryKey": false,
          "notNull": true
        },
        "username": {
          "name": "username",
          "type": "varchar(30)",
          "primaryKey": false,
          "notNull": true
        },
        "password_hash": {
          "name": "password_hash",
          "type": "varchar(255)",
          "primaryKey": false,
          "notNull": true
        },
        "created_at": {
          "name": "created_at",
          "type": "timestamp",
          "primaryKey": false,
          "notNull": true,
          "default": "now()"
        }
      },
      "indexes": {},
      "foreignKeys": {},
      "compositePrimaryKeys": {},
      "uniqueConstraints": {
        "users_email_unique": {
          "name": "users_email_unique",
          "nullsNotDistinct": false,
          "columns": [
            "email"
          ]
        },
        "users_username_unique": {
          "name": "users_username_unique",
          "nullsNotDistinct": false,
          "columns": [
            "username"
          ]
        }
      },
      "policies": {},
      "checkConstraints": {},
      "isRLSEnabled": false
    }
  },
  "enums": {
    "public.friendship_status": {
      "name": "friendship_status",
      "schema": "public",
      "values": [
        "pending",
        "accepted",
        "rejected"
      ]
    }
  },
  "schemas": {},
  "sequences": {},
  "roles": {},
  "policies": {},
  "views": {},
  "_meta": {
    "columns": {},
    "schemas": {},
    "tables": {}
  }
}